{
  "project_name": "mango AI v3 시작",
  "project_goal": "Codex 기반 자동 개발 시스템 완성",
  "stage": "done",
  "progress": 100,
  "codex_mode": "실제 Codex CLI",
  "voice": "준비중",
  "camera": "준비중",
  "last_result": "[precheck 1 rc=0]\nC:\\Program Files\\nodejs\\node.exe\n\n[precheck 2 rc=0]\ncodex-cli 0.121.0\n\n`망고계산기.py`를 작업 폴더에 새로 만들었습니다. Tkinter 기반의 간단한 GUI 계산기이며, `+`, `-`, `*`, `/`, `%`, 소수점, 부호 전환, 전체 삭제, 백스페이스, `=` 계산을 지원합니다. 창 제목과 화면 상단 이름도 `망고계산기`로 맞췄습니다.\n\n문법 검증은 완료했습니다. 실행은 작업 폴더에서 `python 망고계산기.py`로 하면 됩니다.\n\n망고계산기.py",
  "last_workspace": "G:\\내 드라이브\\MANGO_v24_fix3\\workspace\\mango_AI_v3_시작",
  "codex_path": "C:\\Users\\LGe\\AppData\\Roaming\\npm\\codex.cmd",
  "node_path": "C:\\Program Files\\nodejs\\node.exe",
  "last_log_summary": "G:\\내 드라이브\\MANGO_v24_fix3\\logs\\codex_last_summary.txt",
  "auto_loop_enabled": true,
  "auto_loop_max_retry": 2,
  "last_created_files": [
    "auto_loop_game.py",
    "auto_loop_game.pyw",
    "calc_app.py",
    "calc_app.pyw",
    "generated_code.py",
    "generated_code.pyw",
    "mango2_notepad.html",
    "memo 불러오기test.txt",
    "memo 저장test.txt",
    "memo_app.py",
    "memo_app.pyw",
    "notepad_app.py",
    "notepad_app.pyw",
    "망고2호기.py",
    "망고2호기_메모.txt",
    "망고계산기.py",
    "망고계산기.pyw"
  ],
  "avatar_image": "G:\\내 드라이브\\MANGO_v24_fix3\\assets\\mango_avatar.png"
}